<?xml version="1.0" encoding="UTF-8"?><i><chatserver>chat.bilibili.com</chatserver><chatid>800097540</chatid><mission>0</mission><maxlimit>500</maxlimit><state>0</state><real_name>0</real_name><source>k-v</source><d p="54.50100,1,25,16777215,1660219946,0,2398575f,1116764868733693440,10">它是心形的耶</d><d p="69.49500,5,25,15138834,1660219998,0,99931c3c,1116765308212855808,10">你还问别人，自信点，问自己！</d><d p="42.74500,5,25,16707842,1660235516,0,c49ffff3,1116895480308065280,10">让我访问！！！</d><d p="35.36300,1,25,16777215,1660220491,0,db9c1a02,1116769435617970176,10">切菜配音离谱hhhhhhh</d><d p="120.25400,1,25,16777215,1660369479,0,f1e09d03,1118019245347772928,10">不是东北啊，小博在北京啊</d><d p="110.80100,5,25,16707842,1660222522,0,13429393,1116786480715433984,10">我们这里是48块一次</d><d p="105.14200,1,25,16777215,1660222249,0,2ccfe4f0,1116784185449729536,10">蝴蝶诶</d><d p="73.11000,1,25,16777215,1660219740,0,eb7b6d83,1116763138667073024,10">我看不太出对称</d><d p="59.80700,1,25,16777215,1660585062,0,f218a5e3,1119827685393252352,10">哇⊙∀⊙！爱心！</d><d p="92.26800,5,25,15138834,1660364851,0,fd5dc7ce,1117980421536189952,10">小黑子（难视）</d><d p="43.54900,1,25,16777215,1660222052,0,a248b1a9,1116782533238123008,10">这是我可以看的吗</d><d p="72.52100,1,25,16777215,1660276981,0,b79b1c97,1117243311095062528,10">《对称》</d><d p="43.05100,1,25,16777215,1660229549,0,13d85903,1116845422850180352,10">这是我可以看的吗</d><d p="105.55800,1,25,16777215,1660229411,0,ea8b2ce7,1116844266363235840,10">收费...之前去做，看多少个痣收多少次费...</d><d p="107.11800,5,25,16777215,1660222400,0,d39c3c62,1116785451064411904,10">夺钱照一次 有没有价格侠</d><d p="117.21900,1,25,9487136,1662200345,0,b1bde33d,1133377656658813952,10">几十块钱是检查一次还是能把全部都检查完，我全身都是痣，还是不敢去</d><d p="111.71300,1,25,16777215,1660403782,0,14624ebc,1118306992562381824,10">99也是几十块 doge.</d><d p="114.65100,5,25,16776960,1660237361,0,32b0ac7e,1116910953104188928,10">东莞三甲 120元 还要挂号19元</d><d p="97.92100,1,25,16777215,1660221637,0,c949c5bb,1116779057057376256,9">需要收费吗？哈哈哈</d><d p="112.45400,1,25,16777215,1660219884,0,cc309a9f,1116764349093064448,9">我不是心疼钱也不是害怕疼，就是害怕排队……</d><d p="48.54800,1,25,16777215,1660219608,0,c27edc6d,1116762031958224640,9">这是能看的吗</d><d p="108.54000,1,25,15138834,1663072351,0,cfe33ba5,1140692577503279360,9">这是一只飞行的蝙蝠</d><d p="80.97900,1,25,16777215,1662195083,0,66f88096,1133333519704356352,9">合着我留了一堆风险在身上</d><d p="105.09100,1,25,16777215,1660959992,0,30fbbee8,1122972821946112000,9">你们医院的好清楚 我感觉我做检查的医院没有这么清楚</d><d p="122.48500,1,25,16777215,1660805357,0,c3966cf3,1121675649136834816,9">谁说是东北！小博是北京的大夫！</d><d p="119.86800,1,25,16777215,1660735695,0,c633978d,1121091282639646464,9">人家北医三院的</d><d p="57.26900,1,25,16777215,1660553906,0,90b6d62c,1119566331516161024,9">有毛</d><d p="1.98000,1,25,16777215,1660332793,0,c81bbadd,1117711494382128384,9">求一个鼻子上的脂质微丝科普</d><d p="121.37200,1,25,16777215,1660280589,0,ce88da40,1117273576203154944,9">北京的医院预约那得是往两周后看</d><d p="114.63400,1,25,16777215,1660279447,0,b4ad4097,1117263995615581184,9">我们这九十</d><d p="81.77800,1,25,16777215,1660270955,0,f4bb0df8,1117192764447311360,9">这是小博带的学生吗</d><d p="103.41900,1,25,16777215,1660229451,0,ca4c9f38,1116844599550237952,9">当然收费，几十块钱吧</d><d p="108.53900,1,25,16777215,1660227893,0,bafdf060,1116831530510238464,9">多少钱啊</d><d p="107.33400,1,25,16777215,1660227159,0,df4978a4,1116825377021649664,9">一个毛孔两根毛</d><d p="94.09200,1,25,16777215,1660224303,0,db4aae72,1116801418855221504,9">从远处看没有毛，放大了有毛毛诶</d><d p="10.89900,1,25,16777215,1660223699,0,f25703a,1116796347295486720,9">同款鼠标</d><d p="47.73200,1,25,16777215,1660222654,0,3265163a,1116787588003271680,8">索尼e卡口镜头</d><d p="58.05500,5,25,16777215,1660222322,0,d39c3c62,1116784796945928960,8">微距相机？</d><d p="13.59200,1,25,16777215,1660221632,0,b996c2bd,1116779011557574144,8">突出的，上边长毛的，对称的，长在不易摩擦的地方上的一般不会都不会恶变</d><d p="61.06800,1,25,16777215,1660221522,0,ef55630a,1116778087770775296,8">右边像猪肉，捂眼</d><d p="47.65500,1,25,16777215,1660221048,0,3e1bbf86,1116774111738104064,8">小博擦边</d><d p="113.07900,1,25,16777215,1660220838,0,d1921cee,1116772349006699776,8">一个痣几十吗？</d><d p="108.69100,1,25,16777215,1660220098,0,3bad6221,1116766145740032000,8">价格呢</d><d p="84.51800,1,25,16777215,1660219679,0,e049002c,1116762627582933760,8">比我们医院的高级！</d><d p="94.45600,1,25,16777215,1740738395,0,a4afd858,1792202569574221568,8">东百人</d><d p="73.75100,1,25,16777215,1726137613,0,268bcd86,1669722335483328768,8">这还安全</d><d p="106.27400,1,25,16777215,1726104959,0,58e2c65e,1669448412711965440,8">施华诺世奇</d><d p="28.33800,1,25,16777215,1725545853,0,a1c0a5d2,1664758292427851520,8">做这个检查贵吗？</d><d p="106.74200,1,25,16777215,1719750910,0,c5b209fa,1616146790288265984,8">紫巅</d><d p="63.44200,1,25,16777215,1719750852,0,c5b209fa,1616146303136421888,8">螨虫</d><d p="62.44500,1,25,16777215,1711468404,0,363a886b,1546668091260501504,8">我草，有血管啊</d><d p="44.95400,1,25,16777215,1706805004,0,a8e5eaa3,1507548661142651136,8">visa</d><d p="73.41400,1,25,16777215,1691625185,0,d74d9b37,1380211110199928320,8">《对称》</d><d p="124.62800,1,25,16777215,1691136929,0,141f8e4c,1376115317339968768,8">济南100，切一颗痣800</d><d p="43.14100,1,25,16777215,1689425632,0,13f392ff,1361759917333027840,7">我们这里做一次皮肤镜诊断要119。。</d><d p="109.98600,1,25,16777215,1687048680,0,e3ac8b74,1341820599793896960,7">随蝴蝶一起飘散吧（不好意思跑错片场</d><d p="113.87000,1,25,16777215,1685015092,0,3915c0ae,1324761631179560448,7">119四颗</d><d p="67.07200,1,25,16777215,1674281626,0,3198c276,1234722786434481152,7">像烤糊的饼</d><d p="101.67200,1,25,16777215,1669454136,0,d654b873,1194226868245594368,7">血管还会扩张吗？！</d><d p="119.07900,1,25,16777215,1666192752,0,bc5dc877,1166868398068560896,7">一颗四十多吗</d><d p="27.17900,1,25,16777215,1665928077,0,4979c8f7,1164648139890746368,7">北医三院</d><d p="125.80100,1,25,16777215,1663410238,0,a176de2a,1143526975680311040,7">买个MATE50PRO开潜望微距就行</d><d p="22.99000,1,25,16777215,1663410127,0,a176de2a,1143526043580407808,7">mate50pro也可以</d><d p="115.09900,1,25,16777215,1662297539,0,630bcb63,1134192977305075712,7">还好我们公司就有</d><d p="125.46400,1,25,16777215,1661690746,0,4a5a494e,1129102831744496640,7">兄弟上有怎么办</d><d p="116.73100,1,25,16777215,1661656683,0,6d8fea69,1128817094910313728,7">有辐射么</d><d p="46.37900,1,25,16777215,1661559291,0,9185412,1128000104385547264,7">美人痣</d><d p="119.92500,1,25,16777215,1661406076,0,6b1e920a,1126714844356144640,7">门诊检查费报不了吧？</d><d p="89.08600,1,25,16777215,1661272624,0,6c812215,1125595374837585920,7">偏振！！3-4人狂喜</d><d p="126.93200,1,25,16777215,1661222807,0,fe50651d,1125177473093472000,7">他只是东北口音</d><d p="42.38400,1,25,16777215,1661000615,0,593aa5b4,1123313597561396992,7">这是可以看的吗（(✿◡‿◡)</d><d p="32.27700,1,25,16777215,1661000588,0,593aa5b4,1123313366891534336,6">这个音效哈哈哈</d><d p="47.06700,1,25,16777215,1660996326,0,68c07e92,1123277614350472192,6">就是索尼微单的镜头吧</d><d p="120.25900,1,25,16777215,1660989022,0,f49d7399,1123216344419061248,6">我痣太多了，好几十呢</d><d p="64.36300,1,25,16777215,1660923369,0,b4d121fe,1122665609075935488,6">我靠，像是被丧尸病毒感染正在扩散</d><d p="112.93400,1,25,16777215,1660816507,0,a83b3df0,1121769185236489728,6">身上所有的痣全都照吗</d><d p="28.41200,1,25,16777215,1660673916,0,61e1b383,1120573045980112128,6">皮科医生讲什么痔疮，前面的走错科室了</d><d p="28.81900,1,25,16777215,1660547671,0,ee4de39c,1119514025038984704,6">金相显微镜</d><d p="123.45900,1,25,16777215,1660545510,0,c370b0d0,1119495898221577216,6">脸上跟麻花似的，一下几十块꒦ິ^꒦ິ</d><d p="42.96500,5,25,15138834,1660492847,0,d9784bd5,1119054130963433728,6">看看葡萄干</d><d p="79.88200,1,25,16777215,1660485858,0,3fbdb4da,1118995498326467840,6">非偏振反光</d><d p="43.51100,1,25,16777215,1660485803,0,3fbdb4da,1118995036567294464,6">胸口？</d><d p="107.67400,1,25,16777215,1660451968,0,a4feb89d,1118711209500353536,6">还是心形的</d><d p="56.37400,1,25,16777215,1660451907,0,a4feb89d,1118710697233078272,6">连痣也是爱你的形状</d><d p="74.69900,1,25,16777215,1660447113,0,66b43f0,1118670483051735040,6">心形 对称轴是斜的</d><d p="71.49800,1,25,16777215,1660437508,0,42c2a673,1118589909079242240,6">切了</d><d p="107.10500,1,25,16777215,1660422521,0,390c7951,1118464193272479744,6">有颗蓝色的痣。。</d><d p="107.23500,1,25,16777215,1660410390,0,90a16ec4,1118362428401521664,6">前天做完128</d><d p="125.72700,1,25,16777215,1660403419,0,1f2b7b29,1118303955173248256,6">有点想给身上的痣都去留个影</d><d p="100.06000,1,25,16777215,1660403404,0,fab749d4,1118303821760843776,5">我终于知道我隔壁上的血痦子是什么了</d><d p="101.36500,1,25,16777215,1660396680,0,5d79122c,1118247417901539328,5">不洗澡一眼可见</d><d p="7.77500,1,25,16777215,1660392735,0,30277448,1118214330421300224,5">纹身会怎么样</d><d p="107.14600,1,25,16777215,1660390812,0,5ea1a075,1118198200327792896,5">左边的毛孔里有两根毛</d><d p="18.49900,1,25,16777215,1660389696,0,46df5a31,1118188832047661568,5">解剖镜同理。。</d><d p="116.20100,1,25,16777215,1660387659,0,d4cdc15c,1118171745409362688,5">武汉160</d><d p="33.03400,1,25,16777215,1660384648,0,c13848b4,1118146487805848576,5">基本上照了都可以切了，不然怎么赚钱</d><d p="112.41900,1,25,16777215,1660376370,0,4348e092,1118077051782473728,5">《也就几十块钱》</d><d p="27.61900,1,25,16777215,1660376076,0,f38306b7,1118074583711393024,5">初。步。判。断。</d><d p="41.74800,1,25,16777215,1660373889,0,6600002c,1118056237037268480,5">胸有大痔</d><d p="65.29900,1,25,16777215,1660371388,0,afc80b90,1118035255710752256,5">胸毛真粗</d><d p="108.81500,1,25,16777215,1660366764,0,8e82ddd8,1117996463281239552,5">看下丹田张什么样</d><d p="23.17900,1,25,16777215,1660365873,0,aeb5c283,1117988993603216384,5">什么时候讲一讲痔疮</d><d p="127.49900,1,25,16777215,1660365793,0,c0246aff,1117988318898951168,5">前面的站住，小博在北京啊</d><d p="6.43900,1,25,16777215,1660359061,0,f5c2bc70,1117931846538484224,5">今年刚切了两颗，会长大的，就得去切掉</d><d p="118.90500,1,25,16777215,1660359007,0,3725847d,1117931395642210560,5">我去，我上个月刚去你们医院做过皮肤镜，医保后就10几块</d><d p="110.80500,1,25,16777215,1660357677,0,d606227d,1117920240655755776,5">我去做 一百块一次</d><d p="0.63400,1,25,16777215,1660357328,0,571cbb90,1117917307604353792,5">思沃的口罩打钱</d><d p="114.39900,1,25,16777215,1660356638,0,cede3abf,1117911526905533696,4">100多啊</d><d p="0.24300,1,25,16777215,1660321025,0,d4b7cc93,1117612779063584768,4">我脚上原来有一颗大的，后来它没怎么长大，但是旁边又长了四颗小的。。。我要去医院看看了</d><d p="115.42300,1,25,16777215,1660320414,0,90cbbdf2,1117607652332135680,4">你们在东北啊。。。一线城市可能更贵吧，哭</d><d p="63.13400,1,25,16777215,1660309884,0,484a1b7c,1117519321287928064,4">大家快看小博的胸毛</d><d p="52.61900,1,25,16777215,1660303345,0,a780a098,1117464469740520448,4">你头发掉手机屏幕上了</d><d p="61.35500,1,25,16777215,1660301795,0,d874c4c1,1117451469797296128,4">neinei(✧∇✧)</d><d p="35.15000,1,25,16777215,1660299696,0,261775cd,1117433856312604672,4">荔枝上长了痣</d><d p="86.98600,1,25,16777215,1660294534,0,fc2ef13,1117390558009279232,4">鳞状细胞</d><d p="48.46300,1,25,16777215,1660288956,0,31168da1,1117343767075209216,4">，，，</d><d p="41.02000,1,25,16777215,1660283899,0,1d012418,1117301348610708224,4">*头上长痣，可以切么</d><d p="122.56200,1,25,16777215,1660281077,0,84152ff4,1117277670833659392,4">我这里一百2</d><d p="47.21200,1,25,16777215,1660280083,0,a9f4bfc8,1117269332607678208,4">索尼E卡口？（doge）</d><d p="114.86600,1,25,16777215,1660277087,0,b79b1c97,1117244197586660096,4">这还能进医保？</d><d p="20.52100,1,25,16777215,1660276919,0,b79b1c97,1117242791521710080,4">下面长痣呢</d><d p="65.27700,1,25,16777215,1660273364,0,9f3b56e7,1117212974323624704,4">它是心形的耶</d><d p="123.73900,1,25,16777215,1660271890,0,6ea99820,1117200609146400256,4">一次可以都看吗</d><d p="6.85000,1,25,16777215,1660269226,0,2af70482,1117178259210039296,4">帅帅帅</d><d p="113.21400,1,25,16777215,1660265594,0,c0833bad,1117147787105106944,3">我去，我们这边78一次</d><d p="94.08000,1,25,16777215,1660252816,0,11ea5b,1117040603369233408,3">我也想照555</d><d p="90.62000,1,25,16777215,1660252807,0,11ea5b,1117040529717162496,3">好高级</d><d p="45.29900,1,25,16777215,1660252746,0,11ea5b,1117040015545989376,3">笑死</d><d p="17.25100,1,25,16777215,1660250970,0,40a7d184,1117025119919712512,3">老婆贴贴</d><d p="36.10400,1,25,16777215,1660244430,0,14db3539,1116970256720831488,3">怎么那么像照妖镜（doge</d><d p="40.03600,1,25,16777215,1660243773,0,57b36142,1116964740917195264,3">小博那家医院啊？</d><d p="119.62300,1,25,16777215,1660236125,0,ed5e76bb,1116900590958560768,3">去哪个科照呀</d><d p="38.58600,1,25,16777215,1660236034,0,ed5e76bb,1116899826437714944,3">照妖镜吗</d><d p="21.05500,1,25,16777215,1660236016,0,ed5e76bb,1116899676491445504,3">哪家医院</d><d p="109.13900,1,25,16777215,1660234312,0,3fd2191c,1116885381321797120,3">小博最棒</d><d p="11.47900,1,25,16777215,1660234044,0,8b6e762d,1116883128107987200,3">小博，可以讲一下痱子吗</d><d p="106.63300,1,25,16777215,1660233384,0,8d65e45a,1116877597926853376,3">大概多少钱？</d><d p="68.05900,1,25,16777215,1660233382,0,374d17ba,1116877579110896128,3">做过一次，一百块一次</d><d p="7.63900,1,25,16777215,1660232217,0,27980c0f,1116867808714813184,3">老婆贴贴</d><d p="44.91800,1,25,16777215,1660232210,0,ff3d5160,1116867742889439744,3">危！</d><d p="114.75900,1,25,16777215,1660232130,0,391ef009,1116867074132852736,3">一百块，上次我做</d><d p="109.57900,1,25,16777215,1660231939,0,c0ad1c3f,1116865471430583552,3">性感的毛毛</d><d p="53.77500,1,25,16777215,1660231412,0,cde7e205,1116861051028124672,2">h ha ha ha ha h ha</d><d p="116.25600,1,25,16777215,1660231010,0,d525fc3b,1116857682029232896,2">一下48？</d><d p="116.32900,1,25,16777215,1660230516,0,ce0e4740,1116853539281325568,2">几十块一颗？，点痣都不用这么多</d><d p="27.32300,1,25,16777215,1660229572,0,75527632,1116845613841947648,2">7月刚做</d><d p="53.64800,1,25,16777215,1660228131,0,db7d562b,1116833529985009664,2">za</d><d p="38.01900,1,25,16777215,1660228116,0,726b27b9,1116833400440014336,2">也切了</d><d p="118.97900,1,25,16777215,1660227739,0,825052cf,1116830237087410944,2">全身那么多   </d><d p="45.62500,1,25,16777215,1660227382,0,da362e94,1116827244988448768,2">小智</d><d p="99.36900,1,25,16777215,1660227165,0,55f6cf2f,1116825428502617344,2">我身上就很多这个e</d><d p="48.64100,1,25,16777215,1660226735,0,399fadc,1116821817156532480,2">我还说这怎么自己照自己看原来有助手</d><d p="10.48100,1,25,16777215,1660226673,0,399fadc,1116821296081212928,2">某荔浦打钱</d><d p="53.14600,1,25,16777215,1660226523,0,dd5112ca,1116820043142012672,2">索尼的镜头</d><d p="6.62300,1,25,16777215,1660225657,0,69cd41f6,1116812778112500992,2">飞利浦医疗科技</d><d p="69.01100,1,25,16777215,1660225236,0,a9e29035,1116809241240320768,2">这声音好好</d><d p="107.23300,1,25,16777215,1660224886,0,c36d3bd0,1116806311040931072,2">小蝴蝶</d><d p="113.71300,1,25,16777215,1660224330,0,5ae05de8,1116801644097505792,2">隐私部位咋办</d><d p="106.17600,1,25,16777215,1660223843,0,3462b3da,1116797562394089472,2">左图一个五角星</d><d p="9.63700,1,25,16777215,1660223420,0,fff5e3a8,1116794011974316032,2">哇撒</d><d p="69.43300,1,25,16777215,1660223225,0,d13eea7,1116792373243066112,1">可怕</d><d p="43.07800,1,25,16777215,1660223059,0,2efb387e,1116790985649860096,1">？</d><d p="66.35900,1,25,16777215,1660223040,0,811e79d5,1116790823028101376,1">好像是索尼的</d><d p="124.24700,1,25,16777215,1660222671,0,48d641e7,1116787730307779840,1">一个几十吗</d><d p="0.88300,1,25,16777215,1660221902,0,a248b1a9,1116781274996995840,1">好新鲜的老婆！</d><d p="107.77200,1,25,16776960,1660221567,0,affcb932,1116778469519543040,1">要钱 么</d><d p="116.34100,1,25,16777215,1660221498,0,3dee57e9,1116777888323124736,1">那还行</d><d p="50.69900,1,25,16777215,1660221392,0,8968e205,1116777000464331008,1">这是能看的吗</d><d p="57.05000,1,25,16777215,1660221256,0,5d06ad4a,1116775856358980352,1">痦子都是爱我的形状</d><d p="64.37600,1,25,16777215,1660220949,0,b1268e0a,1116773280074718208,1">这么明显</d><d p="8.88500,1,25,16777215,1660220894,0,b1268e0a,1116772818801954816,1">博子</d><d p="116.62700,1,25,16777215,1660220115,0,3bad6221,1116766287901499136,1">对，排队可怕</d><d p="9.75000,1,25,16777215,1660219863,0,ff21f1eb,1116764174576420096,1">小博皮肤好</d><d p="8.40200,1,25,16777215,1660219841,0,150c93ff,1116763985018979584,1">今天可以离小博的长辈近一点惹</d><d p="77.90300,1,25,16777215,1660219816,0,cc309a9f,1116763781511542528,1">还是个心型的哎！</d><d p="93.39200,1,25,16777215,1660219780,0,245443c0,1116763472214904576,1">虽然我也能拍出来</d><d p="83.27300,1,25,16777215,1660219770,0,245443c0,1116763387490249984,1">看不懂</d></i>