<?xml version="1.0" encoding="UTF-8"?><i><chatserver>chat.bilibili.com</chatserver><chatid>736168115</chatid><mission>0</mission><maxlimit>300</maxlimit><state>0</state><real_name>0</real_name><source>k-v</source><d p="49.41300,1,25,16777215,1725794040,0,e61df4fb,1666840234194825472,10">少数是真的，发痒什么的只是一时，如果你还去不断挠那个位置就危险了</d><d p="6.44300,1,25,16777215,1723288169,0,d8d08ae0,1645819465944175872,8">我就是这种</d><d p="34.73900,1,25,16777215,1718585948,0,e61df4fb,1606374380357815808,5">发痒有待考证，不准，不要过于焦虑</d><d p="33.98300,1,25,16777215,1699783859,0,98cdd59e,1448651025098867456,3">只有症状2</d></i>